README.md
pytest_network.py
setup.cfg
setup.py
pytest_network.egg-info/PKG-INFO
pytest_network.egg-info/SOURCES.txt
pytest_network.egg-info/dependency_links.txt
pytest_network.egg-info/entry_points.txt
pytest_network.egg-info/requires.txt
pytest_network.egg-info/top_level.txt