Metadata-Version: 2.1
Name: pytest-network
Version: 0.0.1
Summary: A simple plugin to disable network on socket level.
Home-page: https://github.com/best-doctor/pytest_network
Author: Artem Lomonosov
Author-email: mcproger7@gmail.com
Maintainer: Artem Lomonosov
Maintainer-email: mcproger7@gmail.com
License: MIT
Platform: UNKNOWN
Classifier: Framework :: Pytest
Classifier: Topic :: Software Development :: Testing
Classifier: Programming Language :: Python
Classifier: Programming Language :: Python :: 3.7
Classifier: Programming Language :: Python :: 3.8
